[ 
    {
        "sabor": "Chocolate"
    },
    {
        "sabor": "Vainilla"
    },
    {
        "sabor": "Nutella"
    },
    {
        "sabor": "Stracciatella"
    },
    {
        "sabor": "Lotus Vainilla"
    },
    {
        "sabor": "Kinder"
    },
    {
        "sabor": "Kinder Mix"
    },
    {
        "sabor": "Kinder Bueno"
    },
    {
        "sabor": "CheeseCake"
    },
    {
        "sabor": "Menta"
    },
    {
        "sabor": "Choco Vegano"
    },
    {
        "sabor": "Dulce de Leche"
    },
    {
        "sabor": "Rocher"
    },
    {
        "sabor": "Cremino de Pistacho"
    },
    {
        "sabor": "Lemon Pie"
    },
    {
        "sabor": "Happy Hippo"
    },
    {
        "sabor": "Yogurt"
    },
    {
        "sabor": "Coco"
    },
    {
        "sabor": "Fresa"
    },
    {
        "sabor": "Limon"
    },
    {
        "sabor": "Capo Pino"
    },
    {
        "sabor": "Mascarpone Ddl"
    },
    {
        "sabor": "Choco Blanco"
    },
    {
        "sabor": "Manjarate"
    },
    {
        "sabor": "Mandorla"
    }
]